pts_siglent_psu/__init__.py
pts_siglent_psu/siglent_psu.py
pts_siglent_psu-0.0.1.dist-info/LICENSE.txt
pts_siglent_psu-0.0.1.dist-info/METADATA
pts_siglent_psu-0.0.1.dist-info/WHEEL
pts_siglent_psu-0.0.1.dist-info/top_level.txt
pts_siglent_psu-0.0.1.dist-info/RECORD
